webargs_sanic/__init__.py
webargs_sanic/sanicparser.py
webargs_sanic-2.3.5.dist-info/LICENSE
webargs_sanic-2.3.5.dist-info/METADATA
webargs_sanic-2.3.5.dist-info/WHEEL
webargs_sanic-2.3.5.dist-info/top_level.txt
webargs_sanic-2.3.5.dist-info/RECORD
