Metadata-Version: 2.1
Name: webargs-sanic
Version: 2.3.5
Summary: webargs-sanic provides integration of Webargs with Sanic applications
Home-page: https://github.com/EndurantDevs/webargs-sanic
Author: Endurant Devs, Dmytro Nikolayev
Author-email: info@endurantdev.com
License: MIT
Keywords: webargs-sanic webargs sanic web args validation
Classifier: Intended Audience :: Developers
Classifier: Environment :: Web Environment
Classifier: License :: OSI Approved :: MIT License
Classifier: Natural Language :: English
Classifier: Programming Language :: Python :: 3
Classifier: Programming Language :: Python :: 3.6
Classifier: Programming Language :: Python :: 3.7
Classifier: Programming Language :: Python :: 3.8
Classifier: Programming Language :: Python :: 3.9
Classifier: Topic :: Internet :: WWW/HTTP :: Dynamic Content
Classifier: Development Status :: 5 - Production/Stable
License-File: LICENSE
Requires-Dist: sanic (>=0.8.3)
Requires-Dist: webargs (>=7.0.1)
